mcp_graph_engine/__init__.py
mcp_graph_engine/cypher.py
mcp_graph_engine/graph_engine.py
mcp_graph_engine/matcher.py
mcp_graph_engine/server.py
mcp_graph_engine/session.py
mcp_graph_engine/tools.py
mcp_graph_engine/visualization/__init__.py
mcp_graph_engine/visualization/broadcast.py
mcp_graph_engine/visualization/web_server.py
mcp_graph_engine/visualization/static/d3.min.js
mcp_graph_engine/visualization/static/graph.js
mcp_graph_engine/visualization/static/index.html
mcp_graph_engine-1.0.1.dist-info/licenses/LICENSE
mcp_graph_engine-1.0.1.dist-info/METADATA
mcp_graph_engine-1.0.1.dist-info/WHEEL
mcp_graph_engine-1.0.1.dist-info/entry_points.txt
mcp_graph_engine-1.0.1.dist-info/top_level.txt
mcp_graph_engine-1.0.1.dist-info/RECORD
