Metadata-Version: 2.4
Name: mcp-graph-engine
Version: 1.0.1
Summary: A graph database and analysis tool for AI assistants via MCP
Author: utilitydelta
Maintainer: utilitydelta
License: MIT
Project-URL: Homepage, https://github.com/utilitydelta/mcp-graph-engine
Project-URL: Documentation, https://github.com/utilitydelta/mcp-graph-engine#readme
Project-URL: Repository, https://github.com/utilitydelta/mcp-graph-engine.git
Project-URL: Issues, https://github.com/utilitydelta/mcp-graph-engine/issues
Project-URL: Changelog, https://github.com/utilitydelta/mcp-graph-engine/blob/main/CHANGELOG.md
Keywords: mcp,graph,knowledge-graph,llm,ai-assistant,networkx,cypher
Classifier: Development Status :: 5 - Production/Stable
Classifier: Intended Audience :: Developers
Classifier: License :: OSI Approved :: MIT License
Classifier: Operating System :: OS Independent
Classifier: Programming Language :: Python :: 3
Classifier: Programming Language :: Python :: 3.10
Classifier: Programming Language :: Python :: 3.11
Classifier: Programming Language :: Python :: 3.12
Classifier: Topic :: Scientific/Engineering :: Artificial Intelligence
Classifier: Topic :: Database :: Database Engines/Servers
Requires-Python: >=3.10
License-File: LICENSE
Requires-Dist: mcp>=0.9.0
Requires-Dist: networkx>=3.0
Requires-Dist: numpy<2,>=1.24.0
Requires-Dist: scipy>=1.10.0
Requires-Dist: pydot>=1.4.0
Requires-Dist: grand-cypher>=0.3.0
Requires-Dist: fastapi>=0.100.0
Requires-Dist: uvicorn>=0.24.0
Requires-Dist: websockets>=11.0
Provides-Extra: embeddings
Requires-Dist: sentence-transformers>=2.2.0; extra == "embeddings"
Provides-Extra: dev
Requires-Dist: pytest>=7.0.0; extra == "dev"
Requires-Dist: pytest-asyncio>=0.21.0; extra == "dev"
Requires-Dist: pytest-cov>=4.0.0; extra == "dev"
Requires-Dist: ruff>=0.1.0; extra == "dev"
Dynamic: license-file
